<task taskid="[:" applicationGuid="{FE0D94E0-96B1-468E-BBCF-B0AA4D64B23F}"  ctl_idx="0,[:" public_name="" programIsn="439"  taskIsn="4"  IsOffline="0"  interactive="1"  TaskUniqueSort="A"  AsParent="[:"  returnValueExp="0"  RouterPath="[:"  InDefaultRouterOutlet="[:"  refreshon="[:" nullArithmetic="N" mainprg="0"  isPrg="1"  transId="[:"  DvPosDec="[:"  hasLocate="[:">    <exptable>    <exp id="1" val="AQAAAAAAAAABAAAA" compute_by="D" />    </exptable>    <prop id="46" val="CONFIRMATION_MESSAGE_SIP"/>    <prop id="197" studioValue="E" val="[:"  exp="0"/>    <prop id="457" val="[:"  exp="0"/>    <prop id="198" val="0"/>    <prop id="199" val="B"/>    <prop id="200" val="0"/>    <prop id="475" val="1"/>    <prop id="201" val="0"/>    <prop id="202" val="0"/>    <prop id="203" val="0"/>    <prop id="456" val="1"/>    <prop id="653" val="1"/>    <prop id="639" val="A"/>    <prop id="635" val="A"/>    <prop id="637" val="O"/>    <prop id="619" studioValue="1" val="[:"/>    <prop id="592" studioValue="1" val="[:"/>    <prop id="465" studioValue="R" val="[:"/>    <prop id="204" val="0"/>    <prop id="205" val="0"/>    <prop id="206" val="0"/>    <prop id="233" val="0"/>    <prop id="604" studioValue="O" val=""/>    <prop id="207" studioValue="O" val="[:"/>    <prop id="440" val=""/>    <prop id="446" val="[:"/>    <prop id="463" val="1"/>    <links>
</links>
<dvheader rmpos="3,0" chunk_size="[:" chunk_size_expression="0" compute_by="[:" has_main_tbl="0">    <fldh type="A" storage="1" var_name="pFRAME" table_name="Parameter" size="20" virtual="1" param="1" nullallowed="0" defaultvalue="" picture="20" partOfDataview="0"/>    <fldh type="A" storage="1" var_name="V:Frame" table_name="Virtual" size="18" virtual="1" nullallowed="0" defaultvalue="" init="1" picture="U18"/>    <fldh type="A" storage="1" var_name="V:Engine" table_name="Virtual" size="11" virtual="1" nullallowed="0" defaultvalue="" picture="11"/>    </dvheader>    <forms>    <form formIsn="1" isFrameSet="0" isLegalRcForm="1" PBImagesNumber="6">    <prop id="21" val="0"/>    <prop id="22" val="0"/>    <prop id="23" val="411"/>    <prop id="26" val="0"/>    <prop id="33" val="4"/>    <prop id="34" val="1"/>    <prop id="35" val="1"/>    <prop id="50" val="1"/>    <prop id="51" val="1"/>    <prop id="130" val="0"/>    <prop id="311" val="MESSAGE"/><prop id="318" val="1"/>    <prop id="358" val="12"/>    <prop id="448" val="1"/>    <control type="L" controlIsn="2" horizontalAlignmentIsFromSystemDefault="0"  zorder="0">    <prop id="82" val="7"/>    <prop id="83" val="U"/>    <prop id="19" val="Message"/>    <prop id="21" val="138"/>    <prop id="22" val="0"/>    <prop id="23" val="110"/>    <prop id="46" val="Label2"/>    <prop id="50" val="1"/>    <prop id="51" val="2"/>    <prop id="71" val="0" exp="0"/>    <prop id="130" val="0"/>    </control>    <control type="L" controlIsn="9" horizontalAlignmentIsFromSystemDefault="0"  zorder="1">    <prop id="82" val="23"/>    <prop id="83" val="U"/>    <prop id="19" val="Scanned successfully!!!"/>    <prop id="21" val="138"/>    <prop id="22" val="33"/>    <prop id="23" val="229"/>    <prop id="46" val="Label5"/>    <prop id="50" val="1"/>    <prop id="51" val="2"/>    <prop id="71" val="0" exp="0"/>    <prop id="130" val="0"/>    </control>    <control type="L" controlIsn="12" horizontalAlignmentIsFromSystemDefault="0"  zorder="2">    <prop id="82" val="10"/>    <prop id="83" val="U"/>    <prop id="19" val="FRAME NO -"/>    <prop id="21" val="91"/>    <prop id="22" val="83"/>    <prop id="23" val="95"/>    <prop id="46" val="Label12"/>    <prop id="50" val="1"/>    <prop id="51" val="2"/>    <prop id="71" val="0" exp="0"/>    <prop id="130" val="0"/>    </control>    <control type="T" controlIsn="11" horizontalAlignmentIsFromSystemDefault="0"  zorder="3">    <prop id="21" val="192"/>    <prop id="22" val="83"/>    <prop id="23" val="187"/>    <prop id="46" val="V_VFrame"/>    <prop id="50" val="1"/>    <prop id="51" val="2"/>    <prop id="71" val="0" exp="0"/>    <prop id="719" val="[:"/>    <prop id="733" val="1"/>    <prop id="43" val="0,1"/>    <prop id="83" val="A"/>    <prop id="82" val="U18"/>    </control>    <recompute>    [:</recompute>    </form>    </forms>        <helptable>    [:</helptable>    <eventhandlers>    <handler id="1" handledby="C" level="T" scope="S" enabled="Y" propagate="N">    <event eventtype="I" internalevent="1001"/>    </handler>    <handler id="2" handledby="C" level="T" scope="S" enabled="Y" propagate="N">    <event eventtype="I" internalevent="1002"/>    </handler>    <handler id="3" handledby="C" level="R" scope="S" enabled="Y" propagate="N">    <event eventtype="I" internalevent="1003"/>    </handler>    <handler id="4" handledby="C" level="H" scope="T" enabled="Y" propagate="N">    <event eventtype="T" seconds="3"/>    <oper type="14" wait="N" cnd="Y" serverid="0">    <event eventtype="I" internalevent="14"/>    </oper>    </handler>    </eventhandlers>    </task>    